struct_changelog/__init__.py
struct_changelog/helpers.py
struct_changelog/manager.py
struct_changelog/types.py
struct_changelog-0.2.0.dist-info/LICENSE
struct_changelog-0.2.0.dist-info/METADATA
struct_changelog-0.2.0.dist-info/WHEEL
struct_changelog-0.2.0.dist-info/RECORD
